{"nodes": [{"id": "notebooklm_workflow_hard_rule", "label": "NotebookLM Hard Rule (2026-05-07)", "file_type": "document", "source_file": "MEMORY/notebooklm_workflow.md", "source_location": null, "source_url": null, "captured_at": "2026-05-07", "author": null, "contributor": null}, {"id": "notebooklm_workflow_mcp_tools", "label": "NotebookLM MCP Tools", "file_type": "document", "source_file": "MEMORY/notebooklm_workflow.md", "source_location": null, "source_url": null, "captured_at": null, "author": null, "contributor": null}, {"id": "notebooklm_workflow_notebook_id_deprecated", "label": "Deprecated Notebook ID ed3c8952", "file_type": "document", "source_file": "MEMORY/notebooklm_workflow.md", "source_location": null, "source_url": null, "captured_at": null, "author": null, "contributor": null}, {"id": "notebooklm_workflow_auth_check_sequence", "label": "Session Start Auth Check Sequence", "file_type": "document", "source_file": "MEMORY/notebooklm_workflow.md", "source_location": null, "source_url": null, "captured_at": null, "author": null, "contributor": null}, {"id": "notebooklm_workflow_update_loop", "label": "Update Loop (list/delete/add)", "file_type": "document", "source_file": "MEMORY/notebooklm_workflow.md", "source_location": null, "source_url": null, "captured_at": null, "author": null, "contributor": null}, {"id": "notebooklm_workflow_bootstrap", "label": "Bootstrap 80 Sources", "file_type": "document", "source_file": "MEMORY/notebooklm_workflow.md", "source_location": null, "source_url": null, "captured_at": "2026-05-06", "author": null, "contributor": null}], "edges": [{"source": "notebooklm_workflow_hard_rule", "target": "notebooklm_workflow_mcp_tools", "relation": "calls", "confidence": "EXTRACTED", "confidence_score": 1.0, "source_file": "MEMORY/notebooklm_workflow.md", "source_location": null, "weight": 1.0}, {"source": "notebooklm_workflow_hard_rule", "target": "notebooklm_workflow_notebook_id_deprecated", "relation": "references", "confidence": "EXTRACTED", "confidence_score": 1.0, "source_file": "MEMORY/notebooklm_workflow.md", "source_location": null, "weight": 1.0}, {"source": "notebooklm_workflow_auth_check_sequence", "target": "notebooklm_workflow_hard_rule", "relation": "rationale_for", "confidence": "EXTRACTED", "confidence_score": 1.0, "source_file": "MEMORY/notebooklm_workflow.md", "source_location": null, "weight": 1.0}, {"source": "notebooklm_workflow_update_loop", "target": "notebooklm_workflow_mcp_tools", "relation": "calls", "confidence": "EXTRACTED", "confidence_score": 1.0, "source_file": "MEMORY/notebooklm_workflow.md", "source_location": null, "weight": 1.0}, {"source": "notebooklm_workflow_bootstrap", "target": "notebooklm_workflow_notebook_id_deprecated", "relation": "references", "confidence": "EXTRACTED", "confidence_score": 1.0, "source_file": "MEMORY/notebooklm_workflow.md", "source_location": null, "weight": 1.0}, {"source": "notebooklm_workflow_notebook_id_deprecated", "target": "project_nlm_notebook_id_deprecated", "relation": "semantically_similar_to", "confidence": "INFERRED", "confidence_score": 0.95, "source_file": "MEMORY/notebooklm_workflow.md", "source_location": null, "weight": 1.0}], "hyperedges": []}